Metadata-Version: 1.0
Name: bengali-letters
Version: 0.1.1
Summary: Quiz app for learning Bengali letters.
Home-page: https://github.com/mattyowl/bengali_letters
Author: Matt Hilton
Author-email: matt.hilton@mykolab.com
License: UNKNOWN
Platform: UNKNOWN
